eml2png/__init__.py
eml2png/eml2png.py
eml2png/skeleton.py
eml2png-0.0.2.dist-info/AUTHORS.rst
eml2png-0.0.2.dist-info/LICENSE
eml2png-0.0.2.dist-info/METADATA
eml2png-0.0.2.dist-info/WHEEL
eml2png-0.0.2.dist-info/entry_points.txt
eml2png-0.0.2.dist-info/top_level.txt
eml2png-0.0.2.dist-info/RECORD
