Metadata-Version: 2.1
Name: eml2png
Version: 0.0.2
Summary: Paint the EML to a single PNG image.
Home-page: https://github.com/poipoii/eml2png
Author: poipoii
Author-email: earth.sama@gmail.com
License: mit
Platform: any
Classifier: Development Status :: 4 - Beta
Classifier: Programming Language :: Python
Requires-Python: >=2.7,!=3.0.*,!=3.1.*,!=3.2.*,!=3.3.*
Requires-Dist: imgkit (==1.0.2)
Provides-Extra: testing
Requires-Dist: pytest ; extra == 'testing'
Requires-Dist: pytest-cov ; extra == 'testing'
Requires-Dist: pytest-xvfb ; extra == 'testing'
